imgk/__init__.py
imgk/cli.py
imgk/utils.py
imgk/commands/__init__.py
imgk/commands/convert.py
imgk/commands/crop.py
imgk/commands/filter.py
imgk/commands/metadata.py
imgk/commands/resize.py
imgk-2.0.0.dist-info/METADATA
imgk-2.0.0.dist-info/WHEEL
imgk-2.0.0.dist-info/entry_points.txt
imgk-2.0.0.dist-info/top_level.txt
imgk-2.0.0.dist-info/RECORD
