Metadata-Version: 2.1
Name: imgk
Version: 2.0.0
Summary: Image Processing Utility
Home-page: https://github.com/prak132/imgk_cli
Author: Prakhar Rathore
License: UNKNOWN
Keywords: image-processing utility command-line
Platform: macOS
Requires-Dist: Pillow
